{"channel":{"id":1243605,"name":"Stazione meteo","description":"Ricezione dati dalla stazione meteo a Cros","latitude":"46.04145","longitude":"12.1154","field1":"Temperatura aria","field2":"Umidità aria","field3":"Umidità terreno","field4":"Velocità vento","field5":"Pressione","field6":"Pioggia caduta","created_at":"2020-11-26T18:27:24Z","updated_at":"2020-12-16T21:16:25Z","elevation":"705","last_entry_id":12},"feeds":[{"created_at":"2020-12-22T12:38:08Z","entry_id":1,"field1":"6.72"},{"created_at":"2020-12-22T13:08:20Z","entry_id":2,"field1":"6.12"},{"created_at":"2020-12-22T13:38:33Z","entry_id":3,"field1":"5.49"},{"created_at":"2020-12-22T14:08:48Z","entry_id":4,"field1":"4.88"},{"created_at":"2020-12-22T14:39:03Z","entry_id":5,"field1":"4.48"},{"created_at":"2020-12-22T15:09:15Z","entry_id":6,"field1":"2.95"},{"created_at":"2020-12-22T15:39:27Z","entry_id":7,"field1":"1.55"},{"created_at":"2020-12-22T16:09:39Z","entry_id":8,"field1":"1.05"},{"created_at":"2020-12-22T16:39:51Z","entry_id":9,"field1":"0.88"},{"created_at":"2020-12-22T17:10:02Z","entry_id":10,"field1":"1"},{"created_at":"2020-12-22T17:40:14Z","entry_id":11,"field1":"0.96"},{"created_at":"2020-12-22T18:10:26Z","entry_id":12,"field1":"0.88"}]}
